Workbook

Sheet Read Me
A1: Bryan J. Freedman (SBN 151990) — Consolidated Trellis Data
A4: What this is | B4: One consolidated workbook built from 11 Trellis exports (8 scraped case-list pages, 2 xlsx, 1 csv) plus the BC606196 docket PDF.
A5: Unique cases | B5: 322 after de-duplicating on case number across all source files (470 raw rows ingested).
A7: TABS
A8: All Cases | B8: Every unique case: name, no., filed date, judge, Trellis disposition, an Outcome Bucket, practice area, matter type, court, source file, URL.
A9: Judge Summary | B9: Per-judge appearance counts + disposition breakdown (formulas count live off the All Cases tab).
A10: Disposition Summary | B10: Counts by raw Trellis disposition and by Outcome Bucket.
A11: Liberty BC606196 | B11: The one case you pulled a full 130-pg docket for — case facts + party-level dispositions.
A13: READ THIS — what the data can and cannot tell you
A14: Appearance counts are reliable. | B14: Who Freedman/Freedman+Taitelman has been in front of, and how often, is solid.
A15: Win/loss is NOT in this data. | B15: The only outcome field is case disposition. "Dismissal" is directionally ambiguous (settlement, voluntary, defense win, or plaintiff loss) and which side Freedman was on is not encoded.
A16: Counts include the firm collections docket. | B16: Many rows are Freedman+Taitelman / Banco Popular / Dreier Stein collections matters where the firm was a party. There "Default Judgment" = the firm collecting a debt, not courtroom advocacy. This inflates several judges.
A17: On your "8–12 times" recollection | B17: In the deduped data, only Maureen Duffy-Lewis reaches that band (11). Then a tight cluster of four judges at 7 (Hiroshige, Wiley, Linfield, Green). Trellis’s own profile likely shows higher per-judge numbers because it counts non-deduped appearances/rulings and the firm-as-party docket.
A18: Real merits signal | B18: Lives at the motion/ruling level (e.g., the BC606196 docket), not in these summary cards.

Sheet All Cases
A1: Case Name | B1: Case No | C1: Filed | D1: Judge | E1: Disposition (Trellis) | F1: Outcome Bucket | G1: Practice Area | H1: Matter Type | I1: Court | J1: Source File | K1: URL
A2: MARK YOUSSEF VS KELLY MULHERN ET AL | B2: BC427361 | C2: Dec 04, 2009 | D2: Hon. Abraham Khan | E2: Dismissal | F2: Dismissed/Withdrawn | I2: Stanley Mosk Courthouse | J2: clean_trellis__10__judges-6.xlsx | K2: https://trellis.law/case/bc427361/mark-youssef-vs-kelly-mulhern-et-al
A3: DREIER STEIN KAHAN BROWNE WOODS GEORGE LLP ET AL VS IMAGE EN | B3: BC432833 | C3: Feb 26, 2010 | D3: Hon. Abraham Khan | E3: Dismissal | F3: Dismissed/Withdrawn | G3: Commercial | H3: Breach of Contract | I3: Stanley Mosk Courthouse | J3: clean_trellis__10__judges-2.xlsx | K3: https://trellis.law/case/bc432833/dreier-stein-kahan-browne-woods-george-llp-et-al-vs-image-en
A4: KHALIL RAFATI VS DOES 1 THROUGH 25 | B4: BC509261 | C4: May 17, 2013 | D4: Hon. Abraham Khan | E4: Dismissal | F4: Dismissed/Withdrawn | G4: Torts | H4: Slander,Libel,Defamation | I4: Stanley Mosk Courthouse | J4: clean_trellis__10__judges-1.xlsx | K4: https://trellis.law/case/bc509261/khalil-rafati-vs-does-1-through-25
A5: EH BUTLAND DEVELOPMENT CORP VS JANSS COURT ASSOCIATES LLC | B5: BC263303 | C5: Dec 10, 2001 | D5: Hon. Alban I. Niles | E5: Dismissal | F5: Dismissed/Withdrawn | G5: Creditor | H5: Collections | I5: Stanley Mosk Courthouse | J5: trellis.csv | K5: https://trellis.law/case/bc263303/eh-butland-development-corp-vs-janss-court-associates-llc
A6: RORY POSIN VS BENJAMIN BELLET ET AL | B6: BC490353 | C6: Aug 15, 2012 | D6: Hon. Amy D. Hogue | E6: Dismissal | F6: Dismissed/Withdrawn | G6: Securities | H6: Business Governance | I6: Stanley Mosk Courthouse | J6: trellis.csv | K6: https://trellis.law/case/bc490353/rory-posin-vs-benjamin-bellet-et-al
A7: BANCO POPULAR NORTH AMERICA VS R & J LEGAL SERVICES INC ET A | B7: BC396705 | C7: Aug 20, 2008 | D7: Hon. Amy D. Hogue | E7: Default Judgment | F7: Default Judgment | G7: Commercial | H7: Breach of Contract | I7: Stanley Mosk Courthouse | J7: clean_trellis__10__judges-6.xlsx | K7: https://trellis.law/case/bc396705/banco-popular-north-america-vs-r-j-legal-services-inc-et-a
A8: BANCO POPULAR NORTH AMERICA VS DAELIM INSURANCE AGENCY INC | B8: BC398874 | C8: Jan 09, 2008 | D8: Hon. Amy D. Hogue | E8: Dismissal | F8: Dismissed/Withdrawn | G8: Commercial | H8: Breach of Contract | I8: Stanley Mosk Courthouse | J8: clean_trellis__10__judges-1.xlsx | K8: https://trellis.law/case/bc398874/banco-popular-north-america-vs-daelim-insurance-agency-inc
A9: DREIER STEIN KAHAN BROWNE WOODS GEORGE LLP VS SEOUL NATIONAL | B9: BC433001 | C9: Mar 03, 2010 | D9: Hon. Amy D. Hogue | E9: Dismissal | F9: Dismissed/Withdrawn | G9: Commercial | H9: Breach of Contract | I9: Stanley Mosk Courthouse | J9: clean_trellis__10__judges-6.xlsx | K9: https://trellis.law/case/bc433001/dreier-stein-kahan-browne-woods-george-llp-vs-seoul-national
A10: DREIER STEIN KAHAN BROWNE WOODS GEORGE LLP VS LIOLIOS GROUP | B10: BC434484 | C10: Mar 24, 2010 | D10: Hon. Amy D. Hogue | E10: Dismissal | F10: Dismissed/Withdrawn | G10: Commercial | H10: Breach of Contract | I10: Stanley Mosk Courthouse | J10: clean_trellis__10__judges-1.xlsx | K10: https://trellis.law/case/bc434484/dreier-stein-kahan-browne-woods-george-llp-vs-liolios-group
A11: ST. ANDREWS SECOND HOME LLC, A DELAWARE LIMITED LIABILITY COMPANY VS SECOND HOME US INC., A DELAWARE CORPORATION, ET AL. | B11: 23STCV09293 | C11: Apr 26, 2023 | D11: Hon. Armen Tamzarian | E11: Active | F11: Active | G11: Property | H11: Unlawful Detainer | I11: Stanley Mosk | J11: trellis.xlsx | K11: https://trellis.law/case/23stcv09293/st-andrews-second-home-llc-a-delaware-limited-liability-company-vs-second-home-us-inc-a-delaware-corporation-et-al
A12: REGENCY SAVINGS BANK FSB VS PHILIP A ROSTER | B12: BC191770 | C12: May 28, 1998 | D12: Hon. Arnold Levin | E12: Dismissal | F12: Dismissed/Withdrawn | I12: Stanley Mosk Courthouse | J12: trellis.csv | K12: https://trellis.law/case/bc191770/regency-savings-bank-fsb-vs-philip-a-roster
A13: OLD CHURCH LLC ET AL VS FAR EAST NATIONAL BANK | B13: BC486656 | C13: Jun 14, 2012 | D13: Hon. Barbara Marie Scheper | E13: Summary Judgment | F13: Merits/Judgment | G13: Commercial | H13: Contractual Fraud | I13: Stanley Mosk Courthouse | J13: clean_trellis__10__judges-6.xlsx | K13: https://trellis.law/case/bc486656/old-church-llc-et-al-vs-far-east-national-bank
A14: FREEDMAN & TAITELMAN LLP VS JEDAMIST ET AL | B14: BC458020 | C14: Mar 23, 2011 | D14: Hon. Barbara Marie Scheper | E14: Dismissal | F14: Dismissed/Withdrawn | G14: Commercial | H14: Breach of Contract | I14: Stanley Mosk Courthouse | J14: trellis-_F_T_-49rows.xlsx | K14: https://trellis.law/case/bc458020/freedman-taitelman-llp-vs-jedamist-et-al
A15: LEE & ASSOC COMMERCIAL REAL ESTATE ET AL VS DENNIS SWANSON | B15: BC493574 | C15: Oct 12, 2012 | D15: Hon. Barbara Marie Scheper | E15: Dismissal | F15: Dismissed/Withdrawn | G15: Property | H15: Unlawful Detainer | I15: Stanley Mosk Courthouse | J15: trellis.csv | K15: https://trellis.law/case/bc493574/lee-assoc-commercial-real-estate-et-al-vs-dennis-swanson
A16: GATEWAY BUSINESS BANK VS E F J ENTERPRISE, INC., ET AL | B16: VC039137 | C16: Jan 24, 2003 | D16: Hon. Brian F. Gasdia | E16: Dismissal | F16: Dismissed/Withdrawn | G16: Commercial | H16: Contractual Fraud | I16: Norwalk Courthouse | J16: trellis.xlsx | K16: https://trellis.law/case/vc039137/gateway-business-bank-vs-e-f-j-enterprise-inc-et-al
A17: HUDSON 604 ARIZONA LLC VS REAL OFFICE CENTERS CORP ET AL | B17: BC549149 | C17: Jun 18, 2014 | D17: Hon. Brian S. Currey | E17: Dismissal | F17: Dismissed/Withdrawn | G17: Property | H17: Unlawful Detainer | I17: Stanley Mosk Courthouse | J17: clean_trellis__10__judges-2.xlsx | K17: https://trellis.law/case/bc549149/hudson-604-arizona-llc-vs-real-office-centers-corp-et-al
A18: G.J. DESIGN INC VS PDTW LLC ET AL | B18: BC473809 | C18: Nov 18, 2011 | D18: Hon. Brian S. Currey | E18: Dismissal | F18: Dismissed/Withdrawn | G18: Commercial | H18: Breach of Contract | I18: Stanley Mosk Courthouse | J18: clean_trellis__10__judges-2.xlsx | K18: https://trellis.law/case/bc473809/g-j-design-inc-vs-pdtw-llc-et-al
A19: BANKERS TRUST CO OF CALIF N A VS NOELETHA E LACEY ET AL | B19: BC186587 | C19: Feb 25, 1998 | D19: Hon. Bruce E. Mitchell | E19: Dismissal | F19: Dismissed/Withdrawn | G19: Property | H19: General Property | I19: Stanley Mosk Courthouse | J19: trellis.csv | K19: https://trellis.law/case/bc186587/bankers-trust-co-calif-n-a-vs-noeletha-e-lacey-et-al
A20: SUPERIOR STUCCO & PLASTERING VS. ANDREW CHERNG | B20: GC039002 | C20: May 17, 2007 | D20: Hon. C. Edward Simpson | E20: Dismissal | F20: Dismissed/Withdrawn | I20: Pasadena Courthouse | J20: trellis-_F_T_-49rows.xlsx | K20: https://trellis.law/case/gc039002/superior-stucco-plastering-vs-andrew-cherng
A21: DONALD BROWN VS ALBERTSONS INC | B21: BC294155 | C21: Apr 17, 2003 | D21: Hon. Carl J. West | E21: Dismissal | F21: Dismissed/Withdrawn | G21: Labor and Employment | H21: General Employment | I21: Stanley Mosk Courthouse | J21: trellis.xlsx | K21: https://trellis.law/case/bc294155/donald-brown-vs-albertsons-inc
A22: MARINA HANTZIS VS. JAMES C. BOZZUTO | B22: BS135009 | C22: Dec 20, 2011 | D22: Hon. Carol Boas Goodson | E22: Dismissal | F22: Dismissed/Withdrawn | G22: Torts | H22: Harassment | I22: Stanley Mosk Courthouse | J22: clean_trellis__10__judges-1.xlsx | K22: https://trellis.law/case/bs135009/marina-hantzis-vs-james-c-bozzuto
A23: ALYSON HANNINGAN VS. JOHN HOBBS | B23: BS141494 | C23: Feb 13, 2013 | D23: Hon. Carol Boas Goodson | E23: Judgment (Other) | F23: Merits/Judgment | G23: Torts | H23: Harassment | I23: Stanley Mosk Courthouse | J23: clean_trellis__10__judges-1.xlsx | K23: https://trellis.law/case/bs141494/alyson-hanningan-vs-john-hobbs
A24: RANNIE ANN RODIL VS ROBERT BASSIRI | B24: BS125418 | C24: Mar 16, 2010 | D24: Hon. Carol Boas Goodson | E24: Dismissal | F24: Dismissed/Withdrawn | G24: Torts | H24: Harassment | I24: Stanley Mosk Courthouse | J24: clean_trellis__10__judges-1.xlsx | K24: https://trellis.law/case/bs125418/rannie-ann-rodil-vs-robert-bassiri
A25: EDDIE KWOH VS PAPA ANTONIOS INC ET AL | B25: BC185203 | C25: Jan 30, 1998 | D25: Hon. Carolyn B. Kuhl | E25: Default Judgment | F25: Default Judgment | G25: Commercial | H25: General Commercial | I25: Stanley Mosk Courthouse | J25: trellis.csv | K25: https://trellis.law/case/bc185203/eddie-kwoh-vs-papa-antonios-inc-et-al
A26: SC MANUFACTURED HOMES INC ET AL VS NORMAN SCOTT LIEBERT ET A | B26: BC311686 | C26: Mar 05, 2004 | D26: Hon. Carolyn B. Kuhl | E26: Dismissal | F26: Dismissed/Withdrawn | G26: Antitrust | H26: General Antitrust | I26: Stanley Mosk Courthouse | J26: trellis.xlsx | K26: https://trellis.law/case/bc311686/sc-manufactured-homes-inc-et-al-vs-norman-scott-liebert-et-a
A27: FREEDMAN & TAITELMAN, LLP VS. JANELLE HOLDEN, ET AL | B27: YC056930 | C27: Mar 07, 2008 | D27: Hon. Cary H. Nishimoto | E27: Dismissal | F27: Dismissed/Withdrawn | G27: Commercial | H27: Breach of Contract | I27: Torrance Courthouse | J27: trellis-_F_T_-49rows.xlsx | K27: https://trellis.law/case/yc056930/freedman-taitelman-llp-vs-janelle-holden-et-al
A28: DREIER STEIN KAHAN BROWNE WOODS GEORGE LLP ET AL VS NOBLE EN | B28: BC432802 | C28: Feb 26, 2010 | D28: Hon. Charles F. Palmer | E28: Default Judgment | F28: Default Judgment | G28: Commercial | H28: Breach of Contract | I28: Stanley Mosk Courthouse | J28: clean_trellis__10__judges-3.xlsx | K28: https://trellis.law/case/bc432802/dreier-stein-kahan-browne-woods-george-llp-et-al-vs-noble-en
A29: STEPHEN BARNES VS LAVELY & SINGER ET AL | B29: BC191060 | C29: May 15, 1998 | D29: Hon. Charles W. McCoy, Jr. | E29: Summary Judgment | F29: Merits/Judgment | G29: Torts | H29: Malpractice | I29: Stanley Mosk Courthouse | J29: trellis.csv | K29: https://trellis.law/case/bc191060/stephen-barnes-vs-lavely-singer-et-al
A30: MDS, INC. VS. LANDMARK ENTERTAINMENT GROUP | B30: EC036294 | C30: Feb 25, 2003 | D30: Hon. Charles W. Stoll | E30: Default Judgment | F30: Default Judgment | G30: Commercial | H30: General Commercial | I30: Glendale Courthouse | J30: trellis.csv | K30: https://trellis.law/case/ec036294/mds-inc-vs-landmark-entertainment-group
A31: CHARLES MARMO, ET AL VS. FRANCIS PROPERTY MANAGEMENT | B31: EC042434 | C31: Mar 10, 2006 | D31: Hon. Charles W. Stoll | E31: Want of Prosecution | F31: Dismissed/Withdrawn | G31: Property | H31: Landlord-Tenant | I31: Glendale Courthouse | J31: trellis.csv | K31: https://trellis.law/case/ec042434/charles-marmo-et-al-vs-francis-property-management
A32: SONNY HENTY, ET AL. VS M.MALONE, INC., A CALIFORNIA CORPORATION, ET AL. | B32: 22STCP04455 | C32: Dec 27, 2022 | D32: Hon. Christopher K. Lui | E32: Voluntary Dismissal | F32: Dismissed/Withdrawn | G32: Securities | H32: Business Governance | I32: Stanley Mosk | J32: clean_trellis__10__judges-2.xlsx | K32: https://trellis.law/case/22stcp04455/sonny-henty-et-al-vs-m-malone-inc-a-california-corporation-et-al
... A40: JAMES COPELAND VS RENE GABRIEL HERNANDEZ, ET AL | B40: VC044956 | C40: Aug 04, 2005 | D40: Hon. Daniel S. Pratt | E40: Dismissal | F40: Dismissed/Withdrawn | G40: Torts | H40: Automobile | I40: Norwalk Courthouse | J40: trellis.csv | K40: https://trellis.law/case/vc044956/james-copeland-vs-rene-gabriel-hernandez-et-al
A41: 610 AVENIDA VICTORIA RESTAURANT, LLC VS. MARK GERAGOS | B41: 30-2021-01184881-CU-BC-CJC | C41: Feb 17, 2021 | D41: Hon. David A. Hoffer | E41: Unknown | F41: Other/Unknown | G41: Breach of Contract | I41: Orange County, CA | J41: trellis.csv | K41: https://trellis.law/case/30-2021-01184881-cu-bc-cjc/610-avenida-victoria-restaurant-llc-vs-mark-geragos
A42: 2221 PARK PLACE ASSOCIATES VS DIGITAL MEDIA CAMPUS | B42: BC242152 | C42: Dec 21, 2000 | D42: Hon. David A. Horowitz | E42: Dismissal | F42: Dismissed/Withdrawn | G42: Civil | H42: Injunctive Action | I42: Stanley Mosk Courthouse | J42: trellis.csv | K42: https://trellis.law/case/bc242152/2221-park-place-associates-vs-digital-media-campus
A43: YOUNG, NICOLE VS YOUNG, ANDRE | B43: 20STFL05624 | C43: Jun 29, 2020 | D43: Hon. David J. Cowan | E43: Default Judgment | F43: Default Judgment | G43: Family | H43: Divorce,Separation | I43: Superior | J43: clean_trellis__10__bryan-joel.xlsx | K43: https://trellis.law/case/20stfl05624/young-nicole-vs-young-andre
A44: BRIAN WILLIAM CORMAN ET AL VS ROGER WILLIAM CORMAN ET AL | B44: BC681310 | C44: Oct 26, 2017 | D44: Hon. David J. Cowan | E44: Unknown | F44: Other/Unknown | G44: Torts | H44: Personal Injury | I44: Stanley Mosk Courthouse | J44: trellis.xlsx | K44: https://trellis.law/case/bc681310/brian-william-corman-et-al-vs-roger-william-corman-et-al
A45: SANTA BARBARA BANK & TRUST VS. RAB PRODUCTIONS INC., ET AL | B45: BC290542 | C45: Feb 18, 2003 | D45: Hon. David L. Minning | E45: Dismissal | F45: Dismissed/Withdrawn | G45: Creditor | H45: Collections | I45: Stanley Mosk Courthouse | J45: clean_trellis__10__judges-2.xlsx | K45: https://trellis.law/case/bc290542/santa-barbara-bank-trust-vs-rab-productions-inc-et-al
A46: UNITED TALENT AGENCY INC VS MEDIAMORPH INC ET AL | B46: BC473720 | C46: Nov 17, 2011 | D46: Hon. David L. Minning | E46: Dismissal | F46: Dismissed/Withdrawn | G46: Commercial | H46: Contractual Fraud | I46: Stanley Mosk Courthouse | J46: clean_trellis__10__judges-2.xlsx | K46: https://trellis.law/case/bc473720/united-talent-agency-inc-vs-mediamorph-inc-et-al
A47: MUSE PRODUCTIONS INC., ET AL VS. FRANCIS FORD COPPOLA INC., | B47: BC380989 | C47: Nov 19, 2007 | D47: Hon. David L. Minning | E47: Dismissal | F47: Dismissed/Withdrawn | G47: Commercial | H47: Breach of Contract | I47: Stanley Mosk Courthouse | J47: clean_trellis__10__judges-6.xlsx | K47: https://trellis.law/case/bc380989/muse-productions-inc-et-al-vs-francis-ford-coppola-inc
A48: VIDEO SYMPHONY ENTERTAINING, INC. VS. DEL REY PROPERTIES LLC | B48: EC037326 | C48: Jul 30, 2003 | D48: Hon. David M. Schacter | E48: Dismissal | F48: Dismissed/Withdrawn | G48: Commercial | H48: Breach of Rental | I48: Burbank Courthouse | J48: trellis.csv | K48: https://trellis.law/case/ec037326/video-symphony-entertaining-inc-vs-del-rey-properties-llc
A49: PAUL SHEPHERD ET AL VS JOSHUA ALTMAN ET AL | B49: BC696247 | C49: Feb 27, 2018 | D49: Hon. David Sotelo | E49: Voluntary Dismissal | F49: Dismissed/Withdrawn | G49: Commercial | H49: Contractual Fraud | I49: Stanley Mosk Courthouse | J49: trellis.xlsx | K49: https://trellis.law/case/bc696247/paul-shepherd-et-al-vs-joshua-altman-et-al
A50: ELLEN RAKIETEN VS TARA SENIOR, ET AL. | B50: 19STCV37573 | C50: Oct 18, 2019 | D50: Hon. David Sotelo | E50: Unknown | F50: Other/Unknown | G50: Torts | H50: Malpractice | I50: Stanley Mosk | J50: clean_trellis__10__bryan-joel.xlsx | K50: https://trellis.law/case/19stcv37573/ellen-rakieten-vs-tara-senior-et-al
A51: Vogel v. Trujillo, et al. | B51: 30-2017-00959141-CU-DF-CJC | C51: Dec 04, 2017 | D51: Hon. Deborah C. Servino | E51: Dismissal | F51: Dismissed/Withdrawn | I51: Orange County | J51: trellis-_F_T_-49rows.xlsx | K51: https://trellis.law/case/30-2017-00959141-cu-df-cjc/vogel-v-trujillo-et-al
A52: MAURA MCKILLEN VS EXECUTIVE TREATMENT CORPORATION ET AL | B52: BC500608 | C52: Feb 06, 2013 | D52: Hon. Debre Katz Weintraub | E52: Dismissal | F52: Dismissed/Withdrawn | I52: Stanley Mosk Courthouse | J52: clean_trellis__10__judges-6.xlsx | K52: https://trellis.law/case/bc500608/maura-mckillen-vs-executive-treatment-corporation-et-al
A53: GORSAN BRENTWOOD LLC VS PACIFIC EQUITY REAL ESTATE DEVELOPME | B53: BC496548 | C53: Jan 21, 2001 | D53: Hon. Debre Katz Weintraub | E53: Dismissal | F53: Dismissed/Withdrawn | G53: Civil | H53: Declaratory Action | I53: Stanley Mosk Courthouse | J53: trellis.csv | K53: https://trellis.law/case/bc496548/gorsan-brentwood-llc-vs-pacific-equity-real-estate-developme
A54: DREIER STEIN KAHAN BROWNE WOODS GEORGE LLP ET AL VS CLEARANT | B54: BC433970 | C54: Mar 18, 2010 | D54: Hon. Debre Katz Weintraub | E54: Default Judgment | F54: Default Judgment | G54: Commercial | H54: Breach of Contract | I54: Stanley Mosk Courthouse | J54: clean_trellis__10__judges-2.xlsx | K54: https://trellis.law/case/bc433970/dreier-stein-kahan-browne-woods-george-llp-et-al-vs-clearant
A55: DREIER STEIN KAHAN BROWNE WOODS GEORGE LLP ET AL VS EV REAL | B55: BC458019 | C55: Mar 23, 2011 | D55: Hon. Debre Katz Weintraub | E55: Dismissal | F55: Dismissed/Withdrawn | G55: Commercial | H55: Breach of Contract | I55: Stanley Mosk Courthouse | J55: clean_trellis__10__judges-2.xlsx | K55: https://trellis.law/case/bc458019/dreier-stein-kahan-browne-woods-george-llp-et-al-vs-ev-real
A56: FREEDMAN & TAITELMAN LLP VS GURNEY PRODUCTIONS INC ET AL | B56: BC623107 | C56: Jun 08, 2016 | D56: Hon. Deirdre H. Hill | E56: Jury Verdict | F56: Merits/Judgment | G56: Commercial | H56: Breach of Contract | I56: Stanley Mosk Courthouse | J56: trellis-_F_T_-49rows.xlsx | K56: https://trellis.law/case/bc623107/freedman-taitelman-llp-vs-gurney-productions-inc-et-al
A57: EAST VALLEY CAPITAL PARTNERS VS SUNPAL PARTNERS | B57: BC209326 | C57: Apr 26, 1999 | D57: Hon. Dzintra I. Janavs | E57: Dismissal | F57: Dismissed/Withdrawn | I57: Stanley Mosk Courthouse | J57: trellis.csv | K57: https://trellis.law/case/bc209326/east-valley-capital-partners-vs-sunpal-partners
A58: LIANNA SHAKHNAZARIAN VS FREEDMAN TAITELMAN LLP ET AL | B58: BC691527 | C58: Jan 30, 2018 | D58: Hon. Elaine Lu | E58: Unknown | F58: Other/Unknown | G58: Torts | H58: Malpractice | I58: Stanley Mosk Courthouse | J58: trellis-_F_T_-49rows.xlsx | K58: https://trellis.law/case/bc691527/lianna-shakhnazarian-vs-freedman-taitelman-llp-et-al
A59: ASHLEY JOHNSON, AN INDIVIDUAL, ET AL. VS BRIAN WAYNE FOSTER, AN INDIVIDUAL | B59: 23STCV24055 | C59: Oct 03, 2023 | D59: Hon. Elaine Lu | E59: Active | F59: Active | G59: Torts | H59: Intentional Torts | I59: Stanley Mosk | J59: trellis.xlsx | K59: https://trellis.law/case/23stcv24055/ashley-johnson-an-individual-et-al-vs-brian-wayne-foster-an-individual
A60: GERALD HOFFARTH ET AL VS JACKSON NATIONAL LIFE INSURANCE CO | B60: BC456412 | C60: Jan 01, 1900 | D60: Hon. Elihu M. Berle | E60: Unknown | F60: Other/Unknown | G60: Securities | H60: General Securities | I60: Stanley Mosk Courthouse | J60: trellis.xlsx | K60: https://trellis.law/case/bc456412/gerald-hoffarth-et-al-vs-jackson-national-life-insurance-co
A61: WILLIAM E EMARD VS WAYNE R STRUOSKI | B61: BC212137 | C61: Jun 17, 1999 | D61: Hon. Elihu M. Berle | E61: Dismissal | F61: Dismissed/Withdrawn | G61: Commercial | H61: General Commercial | I61: Stanley Mosk Courthouse | J61: trellis.csv | K61: https://trellis.law/case/bc212137/william-e-emard-vs-wayne-r-struoski
A62: 4 SAME DAY TRANSPORTATION VS NICA, INC. | B62: BC497000 | C62: Dec 06, 2012 | D62: Hon. Elizabeth Allen White | E62: Dismissal | F62: Dismissed/Withdrawn | G62: Commercial | H62: Breach of Contract | I62: Stanley Mosk Courthouse | J62: trellis.csv | K62: https://trellis.law/case/bc497000/4-same-day-transportation-vs-nica-inc
A63: BIG CASEY S LEASING LLC ET AL VS OCTALION LLC ET AL | B63: BC642975 | C63: Dec 07, 2016 | D63: Hon. Elizabeth Allen White | E63: Jury Verdict | F63: Merits/Judgment | I63: Stanley Mosk Courthouse | J63: trellis.csv | K63: https://trellis.law/case/bc642975/big-casey-s-leasing-llc-et-al-vs-octalion-llc-et-al
A64: DREIER STEIN KAHAN BROWNE WOODS ET AL VS DENNIS L KEATING II | B64: BC432324 | C64: Feb 26, 2010 | D64: Hon. Elizabeth Allen White | E64: Default Judgment | F64: Default Judgment | G64: Commercial | H64: Breach of Contract | I64: Stanley Mosk Courthouse | J64: clean_trellis__10__judges-6.xlsx | K64: https://trellis.law/case/bc432324/dreier-stein-kahan-browne-woods-et-al-vs-dennis-l-keating-ii
A65: DREIER STEIN KAHAN BROWNE WOODS GEORGE LLP ET AL VS LEE GABL | B65: BC458135 | C65: Mar 24, 2011 | D65: Hon. Elizabeth Allen White | E65: Dismissal | F65: Dismissed/Withdrawn | G65: Commercial | H65: Breach of Contract | I65: Stanley Mosk Courthouse | J65: clean_trellis__10__judges-2.xlsx | K65: https://trellis.law/case/bc458135/dreier-stein-kahan-browne-woods-george-llp-et-al-vs-lee-gabl
A66: SHUK-BING WONG VS CALLAN MCAULIFFE ET AL | B66: BC618573 | C66: May 12, 2013 | D66: Hon. Elizabeth Allen White | E66: Dismissal | F66: Dismissed/Withdrawn | G66: Property | H66: Unlawful Detainer | I66: Stanley Mosk Courthouse | J66: clean_trellis__10__judges-6.xlsx | K66: https://trellis.law/case/bc618573/shuk-bing-wong-vs-callan-mcauliffe-et-al
A67: NECTARIOS G ZAHAB VS PRUDENTIAL CALIFORNIA REALTY ET AL | B67: BC360125 | C67: Oct 11, 2006 | D67: Hon. Elizabeth Allen White | E67: Dismissal | F67: Dismissed/Withdrawn | G67: Commercial | H67: Breach of Contract | I67: Stanley Mosk Courthouse | J67: clean_trellis__10__judges-2.xlsx | K67: https://trellis.law/case/bc360125/nectarios-g-zahab-vs-prudential-california-realty-et-al
A68: DONALD MOTZKIN VS ERIT SHAMAM, ET AL | B68: LC103036 | C68: Jun 16, 2015 | D68: Hon. Elizabeth Ann Lippitt | E68: Dismissal | F68: Dismissed/Withdrawn | G68: Property | H68: General Property | I68: Stanley Mosk Courthouse | J68: clean_trellis__10__bryan-joel.xlsx | K68: https://trellis.law/case/lc103036/donald-motzkin-vs-erit-shamam-et-al
A69: WESTSIDE ESTATE AGENCY INC VS JAMES RANDALL ET AL | B69: BC577588 | C69: Apr 06, 2015 | D69: Hon. Elizabeth R. Feffer | E69: Jury Verdict | F69: Merits/Judgment | G69: Commercial | H69: Breach of Contract | I69: Stanley Mosk Courthouse | J69: trellis.csv | K69: https://trellis.law/case/bc577588/westside-estate-agency-inc-vs-james-randall-et-al
A70: RESCORE KOREATOWN LLC VS DREAMFORNIA ENTEPRISE INC ET AL | B70: BC605280 | C70: Dec 23, 2015 | D70: Hon. Elizabeth R. Feffer | E70: Dismissal | F70: Dismissed/Withdrawn | G70: Property | H70: Unlawful Detainer | I70: Stanley Mosk Courthouse | J70: trellis.csv | K70: https://trellis.law/case/bc605280/rescore-koreatown-llc-vs-dreamfornia-enteprise-inc-et-al
A71: RANDOLPH, CASSANDRA VS UNDERWOOD, COLTON | B71: 20STRO04869 | C71: Sep 11, 2020 | D71: Hon. Emily T. Spear | E71: Other | F71: Other/Unknown | G71: Family | H71: Domestic Violence | I71: Stanley Mosk | J71: clean_trellis__10__bryan-joel.xlsx | K71: https://trellis.law/case/20stro04869/randolph-cassandra-vs-underwood-colton
A72: SYDNEY HOLLAND VS HEATHER NAYLOR | B72: BC519989 | C72: Aug 30, 2013 | D72: Hon. Ernest M. Hiroshige | E72: Dismissal | F72: Dismissed/Withdrawn | G72: Torts | H72: Personal Injury | I72: Stanley Mosk Courthouse | J72: trellis.csv | K72: https://trellis.law/case/bc519989/sydney-holland-vs-heather-naylor
A73: LOS ROBLES BANK VS AMERICA CALIFORNIA BANK | B73: BC224821 | C73: Feb 15, 2000 | D73: Hon. Ernest M. Hiroshige | E73: Transfer | F73: Other/Unknown | G73: Commercial | H73: Breach of Contract | I73: Stanley Mosk Courthouse | J73: trellis.csv | K73: https://trellis.law/case/bc224821/los-robles-bank-vs-america-california-bank
A74: VALLEYCREST LANDSCAPE DEVELOPMENT INC VS RANCHO MALIBU LLC | B74: BC430755 | C74: Jan 28, 2010 | D74: Hon. Ernest M. Hiroshige | E74: Dismissal | F74: Dismissed/Withdrawn | G74: Commercial | H74: Breach of Contract | I74: Stanley Mosk Courthouse | J74: clean_trellis__10__judges-6.xlsx | K74: https://trellis.law/case/bc430755/valleycrest-landscape-development-inc-vs-rancho-malibu-llc
A75: PENINSULA MERCHANT SYNDICATIONS CORP ET AL VS KIRK MULLEN | B75: BC441475 | C75: Jul 12, 2010 | D75: Hon. Ernest M. Hiroshige | E75: Dismissal | F75: Dismissed/Withdrawn | G75: Commercial | H75: Contractual Fraud | I75: Stanley Mosk Courthouse | J75: clean_trellis__10__judges-6.xlsx | K75: https://trellis.law/case/bc441475/peninsula-merchant-syndications-corp-et-al-vs-kirk-mullen
... A80: DEEP BLUE FINANCIAL L P VS IC PARTNERS LLC ET AL | B80: BC550589 | C80: Jul 03, 2014 | D80: Hon. Frederick C. Shaller | E80: Dismissal | F80: Dismissed/Withdrawn | G80: Creditor | H80: Collections | I80: Stanley Mosk Courthouse | J80: trellis.csv | K80: https://trellis.law/case/bc550589/deep-blue-financial-l-p-vs-ic-partners-llc-et-al
A81: Freedman Taitelman LLP vs. Lori F Weinerman trustee of the Weinerman Family Trust | B81: 56-2016-00481718-CL-BC-VTA | C81: May 13, 2016 | D81: Hon. Frederick H. Bysshe, Jr. | E81: Dismissal | F81: Dismissed/Withdrawn | G81: Breach of Contract | I81: Ventura County | J81: trellis-_F_T_-49rows.xlsx | K81: https://trellis.law/case/56-2016-00481718-cl-bc-vta/freedman-taitelman-llp-vs-lori-f-weinerman-trustee-weinerman-family-trust
A82: SOUTHERN CALIFORNIA BUILDERS VS BUCA INC | B82: BC212722 | C82: Jun 29, 1999 | D82: Hon. Fumiko Hachiya Wasserman | E82: Dismissal | F82: Dismissed/Withdrawn | G82: Property | H82: General Property | I82: Stanley Mosk Courthouse | J82: trellis.csv | K82: https://trellis.law/case/bc212722/southern-california-builders-vs-buca-inc
A83: UNITED TALENT AGENCY INC VS POPPY PETAL EMA ELIZABETH DEVERA | B83: BC549483 | C83: Jun 23, 2014 | D83: Hon. Gail Ruderman Feuer | E83: Dismissal | F83: Dismissed/Withdrawn | G83: Commercial | H83: Breach of Contract | I83: Stanley Mosk Courthouse | J83: trellis.csv | K83: https://trellis.law/case/bc549483/united-talent-agency-inc-vs-poppy-petal-ema-elizabeth-devera
A84: FREEDMAN & TAITELMAN LLP VS SHUCK | B84: RIC526684 | C84: May 15, 2009 | D84: Hon. Gary B. Tranbarger | E84: Dismissal | F84: Dismissed/Withdrawn | G84: General Property | I84: Riverside County | J84: trellis-_F_T_-49rows.xlsx | K84: https://trellis.law/case/ric526684/freedman-taitelman-llp-vs-shuck
A85: Kevin Twiggs et al. vs Meritage Homes of California, Inc., a California Limited Liability Company et al. | B85: STK-CV-UCD-2022-0007454 | C85: Aug 24, 2022 | D85: Hon. George J. Abdallah, Jr. | E85: Active | F85: Active | G85: Torts | H85: Construction | I85: San Joaquin County | J85: trellis.xlsx | K85: https://trellis.law/case/stk-cv-ucd-2022-0007454/kevin-twiggs-et-al-vs-meritage-homes-california-inc-a-california-limited-liability-company-et-al
A86: BAMO,INCORPORATED VS. RANCHO MALIBU | B86: SC104543 | C86: Aug 24, 2009 | D86: Hon. Gerald S. Rosenberg | E86: Dismissal | F86: Dismissed/Withdrawn | G86: Creditor | H86: Collections | I86: Santa Monica Courthouse | J86: trellis.xlsx | K86: https://trellis.law/case/sc104543/bamo-incorporated-vs-rancho-malibu
A87: COLLECTIVE DIGITAL STUDIO, LLC VS DANE BOEDIGHEIMER, ET AL., | B87: BS152232 | C87: Dec 23, 2014 | D87: Hon. Gerald S. Rosenberg | E87: Dismissal | F87: Dismissed/Withdrawn | I87: Stanley Mosk Courthouse | J87: clean_trellis__10__judges-1.xlsx | K87: https://trellis.law/case/bs152232/collective-digital-studio-llc-vs-dane-boedigheimer-et-al
A88: CASEY BENNETT VS JASON "ROCKY" ROMANO | B88: SC125502 | C88: Mar 04, 2016 | D88: Hon. Gerald S. Rosenberg | E88: Dismissal | F88: Dismissed/Withdrawn | G88: Commercial | H88: Contractual Fraud | I88: Stanley Mosk Courthouse | J88: clean_trellis__10__judges-6.xlsx | K88: https://trellis.law/case/sc125502/casey-bennett-vs-jason-rocky-romano
A89: PROLACTA BIOSCIENCE, INC. VS. ELENA TAGGART MEDO | B89: 30-2015-00767116-CU-NP-CJC | C89: Jan 20, 2015 | D89: Hon. Glenda Sanders | E89: Non-Jury Verdict | F89: Merits/Judgment | G89: General Torts | I89: Orange County | J89: trellis.xlsx | K89: https://trellis.law/case/30-2015-00767116-cu-np-cjc/prolacta-bioscience-inc-vs-elena-taggart-medo
A90: EMJAG PRODUCTIONS INC ET AL VS THE WEINSTEIN COMPANY LLC | B90: BC685511 | C90: Dec 01, 2017 | D90: Hon. Gregory Keosian | E90: Voluntary Dismissal | F90: Dismissed/Withdrawn | G90: Commercial | H90: Breach of Contract | I90: Stanley Mosk Courthouse | J90: clean_trellis__10__top-seen-judges.xlsx | K90: https://trellis.law/case/bc685511/emjag-productions-inc-et-al-vs-weinstein-company-llc
A91: REGENT, LP, A CALIFORNIA LIMITED PARTNERSHIP, ET AL. VS DAVID STEINHAFEL, AN INDIVIDUAL, ET AL. | B91: 22STCV02610 | C91: Jan 21, 2022 | D91: Hon. Gregory Keosian | E91: Voluntary Dismissal | F91: Dismissed/Withdrawn | G91: Commercial | H91: Contractual Fraud | I91: Stanley Mosk | J91: trellis.csv | K91: https://trellis.law/case/22stcv02610/regent-lp-a-california-limited-partnership-et-al-vs-david-steinhafel-an-individual-et-al
A92: YASHAR ALI VS LOS ANGELES MAGAZINE, LLC, A CALIFORNIA LIMITED LIABILITY COMPANY | B92: 22STCV18984 | C92: Jun 09, 2022 | D92: Hon. Gregory Keosian | E92: Active | F92: Active | G92: Torts | H92: Slander,Libel,Defamation | I92: Stanley Mosk | J92: clean_trellis__10__top-seen-judges.xlsx | K92: https://trellis.law/case/22stcv18984/yashar-ali-vs-los-angeles-magazine-llc-a-california-limited-liability-company
A93: ROSS LEVINSOHN, AN INDIVIDUAL VS THE ARENA GROUP HOLDINGS, INC., A DELAWARE CORPORATION, ET AL. | B93: 24STCV07320 | C93: Mar 21, 2024 | D93: Hon. Gregory Keosian | E93: Active | F93: Active | G93: Labor and Employment | H93: Wrongful Termination | I93: Superior | J93: clean_trellis__10__top-seen-judges.xlsx | K93: https://trellis.law/case/24stcv07320/ross-levinsohn-an-individual-vs-arena-group-holdings-inc-a-delaware-corporation-et-al
A94: FREEDMAN TAITELMAN LLP VS SAM LUTFI | B94: BC642177 | C94: Nov 30, 2016 | D94: Hon. Gregory Keosian | E94: Dismissal | F94: Dismissed/Withdrawn | G94: Civil | H94: Declaratory Action | I94: Stanley Mosk Courthouse | J94: trellis-_F_T_-49rows.xlsx | K94: https://trellis.law/case/bc642177/freedman-taitelman-llp-vs-sam-lutfi
A95: GERALD SCHNEIDERMAN ET AL VS STEVEN L ZELIG ET AL | B95: BC268643 | C95: Feb 21, 2002 | D95: Hon. Gregory Wilson Alarcon | E95: Dismissal | F95: Dismissed/Withdrawn | G95: Torts | H95: Malpractice | I95: Stanley Mosk Courthouse | J95: clean_trellis__10__judges-2.xlsx | K95: https://trellis.law/case/bc268643/gerald-schneiderman-et-al-vs-steven-l-zelig-et-al
A96: DAVID J CAMEL VS MARK SCHIFFMACHER ET AL | B96: BC357502 | C96: Aug 24, 2006 | D96: Hon. Haley J. Fromholz | E96: Dismissal | F96: Dismissed/Withdrawn | I96: Stanley Mosk Courthouse | J96: clean_trellis__10__judges-2.xlsx | K96: https://trellis.law/case/bc357502/david-j-camel-vs-mark-schiffmacher-et-al
A97: THOMAS KELLEY VS U S FOODSERVICE INC | B97: BC299998 | C97: Jul 31, 2003 | D97: Hon. Haley J. Fromholz | E97: Dismissal | F97: Dismissed/Withdrawn | G97: Labor and Employment | H97: Wrongful Termination | I97: Stanley Mosk Courthouse | J97: clean_trellis__10__judges-2.xlsx | K97: https://trellis.law/case/bc299998/thomas-kelley-vs-u-s-foodservice-inc
A98: MAURICE MARCIANO VS HANS KOSTRZEWSKI | B98: BC191291 | C98: May 19, 1998 | D98: Hon. Haley J. Fromholz | E98: Dismissal | F98: Dismissed/Withdrawn | G98: Commercial | H98: General Commercial | I98: Stanley Mosk Courthouse | J98: trellis.xlsx | K98: https://trellis.law/case/bc191291/maurice-marciano-vs-hans-kostrzewski
A99: CHANG LEE ET AL VS WILSHIRE CHAPMAN PLAZA LLC ET AL | B99: BC296211 | C99: May 22, 2003 | D99: Hon. Haley J. Fromholz | E99: Dismissal | F99: Dismissed/Withdrawn | G99: Torts | H99: Premises Liability | I99: Stanley Mosk Courthouse | J99: clean_trellis__10__judges-2.xlsx | K99: https://trellis.law/case/bc296211/chang-lee-et-al-vs-wilshire-chapman-plaza-llc-et-al
A100: LOS ROBLES BANK VS GALAXY SOFTWARE INC ET AL | B100: BC179101 | C100: Oct 07, 1997 | D100: Hon. Haley J. Fromholz | E100: Dismissal | F100: Dismissed/Withdrawn | I100: Stanley Mosk Courthouse | J100: trellis.xlsx | K100: https://trellis.law/case/bc179101/los-robles-bank-vs-galaxy-software-inc-et-al
A101: WHITNEY R. LEEMAN VS. ARC INTERNATIONAL NORTH AMERICA INC et al | B101: CGC03418025 | C101: Mar 05, 2003 | D101: Hon. Harold E. Kahn | E101: Consolidation | F101: Other/Unknown | G101: Torts | H101: Economic Torts | I101: San Francisco County | J101: trellis.xlsx | K101: https://trellis.law/case/cgc03418025/whitney-r-leeman-vs-arc-international-north-america-inc-et-al
A102: LIBERTY MEDIA GROUP, LLC, ET AL., VS NATIONAL PROMOTIONS AND | B102: SC126900 | C102: Jan 06, 2017 | D102: Hon. Harry Jay Ford III | E102: Trial Verdict | F102: Other/Unknown | G102: Commercial | H102: Breach of Contract | I102: Stanley Mosk Courthouse | J102: clean_trellis__10__bryan-joel.xlsx | K102: https://trellis.law/case/sc126900/liberty-media-group-llc-et-al-vs-national-promotions
A103: HERRICK PRODUCTIONS, LLC, A DELAWARE LIMITED LIABILITY COMPANY VS MATTEL, INC., A DELAWARE CORPORATION | B103: 19SMCV01209 | C103: Jul 03, 2019 | D103: Hon. Harry Jay Ford III | E103: Jury Verdict | F103: Merits/Judgment | G103: Commercial | H103: Contractual Fraud | I103: Superior | J103: clean_trellis__10__bryan-joel.xlsx | K103: https://trellis.law/case/19smcv01209/herrick-productions-llc-a-delaware-limited-liability-company-vs-mattel-inc-a-delaware-corporation
A104: THOMAS R. TAMAYO, III VS. LYNNE ANN STEINMAN | B104: PC039274 | C104: Aug 14, 2006 | D104: Hon. Holly E. Kendig | E104: Judgment on Appeal | F104: Other/Unknown | G104: Commercial | H104: Contractual Fraud | I104: Chatsworth Courthouse | J104: trellis-_F_T_-49rows.xlsx | K104: https://trellis.law/case/pc039274/thomas-r-tamayo-iii-vs-lynne-ann-steinman
A105: WILLIAM H CRABEL VS SALVADOR CASTILLO III | B105: BC547893 | C105: Jun 05, 2014 | D105: Hon. Holly E. Kendig | E105: Dismissal | F105: Dismissed/Withdrawn | G105: Commercial | H105: Breach of Contract | I105: Stanley Mosk Courthouse | J105: trellis.csv | K105: https://trellis.law/case/bc547893/william-h-crabel-vs-salvador-castillo-iii
A106: ARNOLD GREENSPAN VS CAROL PERRIN ET AL | B106: BC400491 | C106: Oct 23, 2008 | D106: Hon. Holly E. Kendig | E106: Dismissal | F106: Dismissed/Withdrawn | G106: Commercial | H106: General Commercial | I106: Stanley Mosk Courthouse | J106: trellis.xlsx | K106: https://trellis.law/case/bc400491/arnold-greenspan-vs-carol-perrin-et-al
A107: JORDAN LEE INC VS BARBARA GOLDSMITH | B107: BC687377 | C107: Dec 15, 2017 | D107: Hon. Holly J. Fujie | E107: Dismissal | F107: Dismissed/Withdrawn | G107: Commercial | H107: Breach of Contract | I107: Stanley Mosk Courthouse | J107: trellis.csv | K107: https://trellis.law/case/bc687377/jordan-lee-inc-vs-barbara-goldsmith
A108: MICHAEL E. KASSAN VS BRYAN JOEL FREEDMAN, ET AL. | B108: 24STCV07943 | C108: Mar 28, 2024 | D108: Hon. Holly J. Fujie | E108: Active | F108: Active | G108: Torts | H108: Slander,Libel,Defamation | I108: Superior | J108: clean_trellis__10__bryan-joel.xlsx | K108: https://trellis.law/case/24stcv07943/michael-e-kassan-vs-bryan-joel-freedman-et-al
A109: ARI D. BASS, AN INDIVIDUAL VS LOTUS DOMAINE MANAGEMENT, LLC, A DELAWARE LIMITED LIABILITY COMPANY | B109: 23STCV27319 | C109: Nov 07, 2023 | D109: Hon. Holly J. Fujie | E109: Active | F109: Active | G109: Commercial | H109: Breach of Contract | I109: Stanley Mosk | J109: trellis.xlsx | K109: https://trellis.law/case/23stcv27319/ari-d-bass-an-individual-vs-lotus-domaine-management-llc-a-delaware-limited-liability-company
A110: ASHLEY JORDAN WALLENS VS MEDIA LINK, LLC | B110: 22VECV00578 | C110: Apr 25, 2022 | D110: Hon. Huey P. Cotton, Jr. | E110: Dismissal | F110: Dismissed/Withdrawn | G110: Torts | H110: Personal Injury | I110: Van Nuys East | J110: clean_trellis__10__bryan-joel.xlsx | K110: https://trellis.law/case/22vecv00578/ashley-jordan-wallens-vs-media-link-llc
A111: JANE DOE VS KIRSHNIK KHARI BALL | B111: 20STCV29465 | C111: Aug 05, 2020 | D111: Hon. Huey P. Cotton, Jr. | E111: Active | F111: Active | G111: Torts | H111: Personal Injury | I111: Superior | J111: trellis.csv | K111: https://trellis.law/case/20stcv29465/jane-doe-vs-kirshnik-khari-ball
...

Sheet Judge Summary
A1: Appearances by Judge (counts pull live from the All Cases tab)
A3: Judge | B3: Total Cases | C3: Dismissed/Withdrawn | D3: Default Judgment | E3: Active | F3: Merits/Judgment | G3: Other/Unknown
A4: Hon. Maureen Duffy-Lewis | B4: =COUNTIF('All Cases'!$D$2:$D$323,A4) -> 11 | C4: =COUNTIFS('All Cases'!$D$2:$D$323,A4,'All Cases'!$F$2:$F$323,"Dismissed/Withdrawn") -> 6 | D4: =COUNTIFS('All Cases'!$D$2:$D$323,A4,'All Cases'!$F$2:$F$323,"Default Judgment") -> 2 | E4: =COUNTIFS('All Cases'!$D$2:$D$323,A4,'All Cases'!$F$2:$F$323,"Active") -> 3 | F4: =COUNTIFS('All Cases'!$D$2:$D$323,A4,'All Cases'!$F$2:$F$323,"Merits/Judgment") -> 0 | G4: =COUNTIFS('All Cases'!$D$2:$D$323,A4,'All Cases'!$F$2:$F$323,"Other/Unknown") -> 0
A5: Unknown | B5: =COUNTIF('All Cases'!$D$2:$D$323,A5) -> 10 | C5: =COUNTIFS('All Cases'!$D$2:$D$323,A5,'All Cases'!$F$2:$F$323,"Dismissed/Withdrawn") -> 4 | D5: =COUNTIFS('All Cases'!$D$2:$D$323,A5,'All Cases'!$F$2:$F$323,"Default Judgment") -> 2 | E5: =COUNTIFS('All Cases'!$D$2:$D$323,A5,'All Cases'!$F$2:$F$323,"Active") -> 1 | F5: =COUNTIFS('All Cases'!$D$2:$D$323,A5,'All Cases'!$F$2:$F$323,"Merits/Judgment") -> 1 | G5: =COUNTIFS('All Cases'!$D$2:$D$323,A5,'All Cases'!$F$2:$F$323,"Other/Unknown") -> 2
A6: Hon. Ernest M. Hiroshige | B6: =COUNTIF('All Cases'!$D$2:$D$323,A6) -> 7 | C6: =COUNTIFS('All Cases'!$D$2:$D$323,A6,'All Cases'!$F$2:$F$323,"Dismissed/Withdrawn") -> 5 | D6: =COUNTIFS('All Cases'!$D$2:$D$323,A6,'All Cases'!$F$2:$F$323,"Default Judgment") -> 1 | E6: =COUNTIFS('All Cases'!$D$2:$D$323,A6,'All Cases'!$F$2:$F$323,"Active") -> 0 | F6: =COUNTIFS('All Cases'!$D$2:$D$323,A6,'All Cases'!$F$2:$F$323,"Merits/Judgment") -> 0 | G6: =COUNTIFS('All Cases'!$D$2:$D$323,A6,'All Cases'!$F$2:$F$323,"Other/Unknown") -> 1
A7: Hon. John Shepard Wiley, Jr. | B7: =COUNTIF('All Cases'!$D$2:$D$323,A7) -> 7 | C7: =COUNTIFS('All Cases'!$D$2:$D$323,A7,'All Cases'!$F$2:$F$323,"Dismissed/Withdrawn") -> 6 | D7: =COUNTIFS('All Cases'!$D$2:$D$323,A7,'All Cases'!$F$2:$F$323,"Default Judgment") -> 0 | E7: =COUNTIFS('All Cases'!$D$2:$D$323,A7,'All Cases'!$F$2:$F$323,"Active") -> 0 | F7: =COUNTIFS('All Cases'!$D$2:$D$323,A7,'All Cases'!$F$2:$F$323,"Merits/Judgment") -> 1 | G7: =COUNTIFS('All Cases'!$D$2:$D$323,A7,'All Cases'!$F$2:$F$323,"Other/Unknown") -> 0
A8: Hon. Michael P. Linfield | B8: =COUNTIF('All Cases'!$D$2:$D$323,A8) -> 7 | C8: =COUNTIFS('All Cases'!$D$2:$D$323,A8,'All Cases'!$F$2:$F$323,"Dismissed/Withdrawn") -> 4 | D8: =COUNTIFS('All Cases'!$D$2:$D$323,A8,'All Cases'!$F$2:$F$323,"Default Judgment") -> 0 | E8: =COUNTIFS('All Cases'!$D$2:$D$323,A8,'All Cases'!$F$2:$F$323,"Active") -> 3 | F8: =COUNTIFS('All Cases'!$D$2:$D$323,A8,'All Cases'!$F$2:$F$323,"Merits/Judgment") -> 0 | G8: =COUNTIFS('All Cases'!$D$2:$D$323,A8,'All Cases'!$F$2:$F$323,"Other/Unknown") -> 0
A9: Hon. Terry A. Green | B9: =COUNTIF('All Cases'!$D$2:$D$323,A9) -> 7 | C9: =COUNTIFS('All Cases'!$D$2:$D$323,A9,'All Cases'!$F$2:$F$323,"Dismissed/Withdrawn") -> 6 | D9: =COUNTIFS('All Cases'!$D$2:$D$323,A9,'All Cases'!$F$2:$F$323,"Default Judgment") -> 1 | E9: =COUNTIFS('All Cases'!$D$2:$D$323,A9,'All Cases'!$F$2:$F$323,"Active") -> 0 | F9: =COUNTIFS('All Cases'!$D$2:$D$323,A9,'All Cases'!$F$2:$F$323,"Merits/Judgment") -> 0 | G9: =COUNTIFS('All Cases'!$D$2:$D$323,A9,'All Cases'!$F$2:$F$323,"Other/Unknown") -> 0
A10: Hon. Elizabeth Allen White | B10: =COUNTIF('All Cases'!$D$2:$D$323,A10) -> 6 | C10: =COUNTIFS('All Cases'!$D$2:$D$323,A10,'All Cases'!$F$2:$F$323,"Dismissed/Withdrawn") -> 4 | D10: =COUNTIFS('All Cases'!$D$2:$D$323,A10,'All Cases'!$F$2:$F$323,"Default Judgment") -> 1 | E10: =COUNTIFS('All Cases'!$D$2:$D$323,A10,'All Cases'!$F$2:$F$323,"Active") -> 0 | F10: =COUNTIFS('All Cases'!$D$2:$D$323,A10,'All Cases'!$F$2:$F$323,"Merits/Judgment") -> 1 | G10: =COUNTIFS('All Cases'!$D$2:$D$323,A10,'All Cases'!$F$2:$F$323,"Other/Unknown") -> 0
A11: Hon. Susan Bryant-Deason | B11: =COUNTIF('All Cases'!$D$2:$D$323,A11) -> 6 | C11: =COUNTIFS('All Cases'!$D$2:$D$323,A11,'All Cases'!$F$2:$F$323,"Dismissed/Withdrawn") -> 5 | D11: =COUNTIFS('All Cases'!$D$2:$D$323,A11,'All Cases'!$F$2:$F$323,"Default Judgment") -> 1 | E11: =COUNTIFS('All Cases'!$D$2:$D$323,A11,'All Cases'!$F$2:$F$323,"Active") -> 0 | F11: =COUNTIFS('All Cases'!$D$2:$D$323,A11,'All Cases'!$F$2:$F$323,"Merits/Judgment") -> 0 | G11: =COUNTIFS('All Cases'!$D$2:$D$323,A11,'All Cases'!$F$2:$F$323,"Other/Unknown") -> 0
A12: Hon. Mel Red Recana | B12: =COUNTIF('All Cases'!$D$2:$D$323,A12) -> 5 | C12: =COUNTIFS('All Cases'!$D$2:$D$323,A12,'All Cases'!$F$2:$F$323,"Dismissed/Withdrawn") -> 4 | D12: =COUNTIFS('All Cases'!$D$2:$D$323,A12,'All Cases'!$F$2:$F$323,"Default Judgment") -> 0 | E12: =COUNTIFS('All Cases'!$D$2:$D$323,A12,'All Cases'!$F$2:$F$323,"Active") -> 0 | F12: =COUNTIFS('All Cases'!$D$2:$D$323,A12,'All Cases'!$F$2:$F$323,"Merits/Judgment") -> 1 | G12: =COUNTIFS('All Cases'!$D$2:$D$323,A12,'All Cases'!$F$2:$F$323,"Other/Unknown") -> 0
A13: Hon. Ronald M. Sohigian | B13: =COUNTIF('All Cases'!$D$2:$D$323,A13) -> 5 | C13: =COUNTIFS('All Cases'!$D$2:$D$323,A13,'All Cases'!$F$2:$F$323,"Dismissed/Withdrawn") -> 3 | D13: =COUNTIFS('All Cases'!$D$2:$D$323,A13,'All Cases'!$F$2:$F$323,"Default Judgment") -> 1 | E13: =COUNTIFS('All Cases'!$D$2:$D$323,A13,'All Cases'!$F$2:$F$323,"Active") -> 0 | F13: =COUNTIFS('All Cases'!$D$2:$D$323,A13,'All Cases'!$F$2:$F$323,"Merits/Judgment") -> 0 | G13: =COUNTIFS('All Cases'!$D$2:$D$323,A13,'All Cases'!$F$2:$F$323,"Other/Unknown") -> 1
A14: Hon. Robert Leslie Hess | B14: =COUNTIF('All Cases'!$D$2:$D$323,A14) -> 5 | C14: =COUNTIFS('All Cases'!$D$2:$D$323,A14,'All Cases'!$F$2:$F$323,"Dismissed/Withdrawn") -> 4 | D14: =COUNTIFS('All Cases'!$D$2:$D$323,A14,'All Cases'!$F$2:$F$323,"Default Judgment") -> 0 | E14: =COUNTIFS('All Cases'!$D$2:$D$323,A14,'All Cases'!$F$2:$F$323,"Active") -> 0 | F14: =COUNTIFS('All Cases'!$D$2:$D$323,A14,'All Cases'!$F$2:$F$323,"Merits/Judgment") -> 1 | G14: =COUNTIFS('All Cases'!$D$2:$D$323,A14,'All Cases'!$F$2:$F$323,"Other/Unknown") -> 0
A15: Hon. Richard L. Fruin, Jr. | B15: =COUNTIF('All Cases'!$D$2:$D$323,A15) -> 5 | C15: =COUNTIFS('All Cases'!$D$2:$D$323,A15,'All Cases'!$F$2:$F$323,"Dismissed/Withdrawn") -> 4 | D15: =COUNTIFS('All Cases'!$D$2:$D$323,A15,'All Cases'!$F$2:$F$323,"Default Judgment") -> 1 | E15: =COUNTIFS('All Cases'!$D$2:$D$323,A15,'All Cases'!$F$2:$F$323,"Active") -> 0 | F15: =COUNTIFS('All Cases'!$D$2:$D$323,A15,'All Cases'!$F$2:$F$323,"Merits/Judgment") -> 0 | G15: =COUNTIFS('All Cases'!$D$2:$D$323,A15,'All Cases'!$F$2:$F$323,"Other/Unknown") -> 0
... A162: Hon. Frederick C. Shaller | B162: =COUNTIF('All Cases'!$D$2:$D$323,A162) -> 1 | C162: =COUNTIFS('All Cases'!$D$2:$D$323,A162,'All Cases'!$F$2:$F$323,"Dismissed/Withdrawn") -> 1 | D162: =COUNTIFS('All Cases'!$D$2:$D$323,A162,'All Cases'!$F$2:$F$323,"Default Judgment") -> 0 | E162: =COUNTIFS('All Cases'!$D$2:$D$323,A162,'All Cases'!$F$2:$F$323,"Active") -> 0 | F162: =COUNTIFS('All Cases'!$D$2:$D$323,A162,'All Cases'!$F$2:$F$323,"Merits/Judgment") -> 0 | G162: =COUNTIFS('All Cases'!$D$2:$D$323,A162,'All Cases'!$F$2:$F$323,"Other/Unknown") -> 0

Sheet Disposition Summary
A1: By raw Trellis disposition
A3: Disposition | B3: Count
A4: Dismissal | B4: =COUNTIF('All Cases'!$E$2:$E$323,A4) -> 170
A5: Voluntary Dismissal | B5: =COUNTIF('All Cases'!$E$2:$E$323,A5) -> 34
A6: Active | B6: =COUNTIF('All Cases'!$E$2:$E$323,A6) -> 31
A7: Default Judgment | B7: =COUNTIF('All Cases'!$E$2:$E$323,A7) -> 28
A8: Unknown | B8: =COUNTIF('All Cases'!$E$2:$E$323,A8) -> 11
A9: Other | B9: =COUNTIF('All Cases'!$E$2:$E$323,A9) -> 7
A10: Want of Prosecution | B10: =COUNTIF('All Cases'!$E$2:$E$323,A10) -> 6
A11: Judgment (Other) | B11: =COUNTIF('All Cases'!$E$2:$E$323,A11) -> 6
A12: Jury Verdict | B12: =COUNTIF('All Cases'!$E$2:$E$323,A12) -> 6
A13: Non-Jury Verdict | B13: =COUNTIF('All Cases'!$E$2:$E$323,A13) -> 4
A14: Removal | B14: =COUNTIF('All Cases'!$E$2:$E$323,A14) -> 4
A15: Consolidation | B15: =COUNTIF('All Cases'!$E$2:$E$323,A15) -> 3
... A24: Stayed | B24: =COUNTIF('All Cases'!$E$2:$E$323,A24) -> 1
A25: TOTAL | B25: =SUM(B4:B24) -> 322
A28: By Outcome Bucket
A29: Bucket | B29: Count
A30: Dismissed/Withdrawn | B30: =COUNTIF('All Cases'!$F$2:$F$323,A30) -> 210
A31: Default Judgment | B31: =COUNTIF('All Cases'!$F$2:$F$323,A31) -> 28
A32: Active | B32: =COUNTIF('All Cases'!$F$2:$F$323,A32) -> 31
A33: Merits/Judgment | B33: =COUNTIF('All Cases'!$F$2:$F$323,A33) -> 19
A34: Other/Unknown | B34: =COUNTIF('All Cases'!$F$2:$F$323,A34) -> 34
A35: TOTAL | B35: =SUM(B30:B34) -> 322

Sheet Liberty BC606196
A1: LIBERTY MEDIA GROUP LLC ET AL v. CINECAUSE LLC ET AL — BC606196
A3: Court | B3: Stanley Mosk Courthouse (LA County Superior)
A4: Judge | B4: Hon. Michael P. Linfield (civil)
A5: Filed | B5: Jan 5, 2016
A6: Disposition | B6: Court-Ordered Dismissal — Other
A7: Verdict | B7: Unclassified
A8: Practice Area / Matter | B8: Commercial / Breach of Contract
A9: Plaintiffs | B9: Liberty Media Group LLC; Community Redevelopment Association LLC; General Barricade LLC
A10: Plaintiffs’ counsel | B10: Freedman + Taitelman LLP
A11: Source | B11: 130-page Trellis docket (refreshed May 23, 2026)
A12: Note | B12: This is the one matter with full docket depth — the place to read actual motion-by-motion outcomes. Say the word and I’ll extract the docket timeline into its own tab.
A14: Defendants (party-level disposition from docket)
A15: Defendant | B15: Status
A16: Barnett, Courtney | B16: Dismissed
A17: Cinecause LLC | B17: Active party (Ps)
A18: Fitzgerald, Jon | B18: Dismissed
A19: Gilead Sciences Inc | B19: Active party (Ps)
A20: Goldenvoice LLC
A21: Grant, Lalanii Rochelle | B21: Dismissed
A22: Hollywood Film Festival | B22: Dismissed
A23: Hozier-Byrne, Andrew (Hozier)
A24: Jarvis, Shaun | B24: Dismissed
A25: Moderne Communications Inc | B25: Doe 1
A26: Mosaic L.A. | B26: Active party (Ps)
A27: Parks, Brad | B27: Dismissed
A28: Postergiant Inc | B28: Doe 2
A29: One-Distribution Company LLC
A30: K-Swiss Global Brands | B30: Active party (Ps)
